cf2tf/__init__.py
cf2tf/app.py
cf2tf/cloudformation/__init__.py
cf2tf/cloudformation/_template.py
cf2tf/conversion/__init__.py
cf2tf/conversion/expressions.py
cf2tf/conversion/overrides.py
cf2tf/convert.py
cf2tf/save.py
cf2tf/terraform/__init__.py
cf2tf/terraform/_configuration.py
cf2tf/terraform/blocks.py
cf2tf/terraform/code.py
cf2tf/terraform/doc_file.py
cf2tf/terraform/hcl2/__init__.py
cf2tf/terraform/hcl2/_block.py
cf2tf/terraform/hcl2/complex.py
cf2tf/terraform/hcl2/custom.py
cf2tf/terraform/hcl2/primitive.py
cf2tf-0.9.1.dist-info/LICENSE.txt
cf2tf-0.9.1.dist-info/METADATA
cf2tf-0.9.1.dist-info/WHEEL
cf2tf-0.9.1.dist-info/entry_points.txt
cf2tf-0.9.1.dist-info/RECORD
