Metadata-Version: 2.1
Name: cf2tf
Version: 0.9.1
Summary: Convert Cloudformation Templates to Terraform.
Home-page: https://github.com/DontShaveTheYak/cf2tf
License: GPL-3.0-only
Keywords: cloudformation,terraform,cf2tf,convert,cloud,conversion
Author: Levi Blaney
Author-email: shadycuz@gmail.com
Requires-Python: >=3.9,<3.14
Classifier: License :: OSI Approved :: GNU General Public License v3 (GPLv3)
Classifier: Programming Language :: Python :: 3
Classifier: Programming Language :: Python :: 3.9
Classifier: Programming Language :: Python :: 3.10
Classifier: Programming Language :: Python :: 3.11
Requires-Dist: GitPython (>=3.1.27,<4.0.0)
Requires-Dist: PyYAML (>=6.0,<7.0)
Requires-Dist: cfn-flip (>=1.3.0,<2.0.0)
Requires-Dist: click (>=8.1.2,<9.0.0)
Requires-Dist: click-log (>=0.4.0,<0.5.0)
Requires-Dist: pytest (>=8.0.0,<9.0.0)
Requires-Dist: requests (>=2.27.1,<3.0.0)
Requires-Dist: thefuzz[speedup] (>=0.22.0,<0.23.0)
Project-URL: Repository, https://github.com/DontShaveTheYak/cf2tf
